opset/__init__.py
opset/configurator.py
opset/gcp_secret_handler.py
opset/py.typed
opset/utils.py
opset-4.2.0.dist-info/METADATA
opset-4.2.0.dist-info/WHEEL
opset-4.2.0.dist-info/licenses/LICENSE
opset-4.2.0.dist-info/RECORD
