Metadata-Version: 2.4
Name: opset
Version: 4.2.0
Summary: A library for simplifying the configuration of Python applications at all stages of deployment.
Author-email: Marc-André Dufresne <marc.andre.dufresne@gmail.com>, Alexandre Jutras <jutras.alexandre@gmail.com>
License-Expression: Apache-2.0
License-File: LICENSE
Keywords: config,configuration,logging,management,setup
Requires-Python: <4.0,>=3.10
Requires-Dist: colorama<1.0,>=0.4
Requires-Dist: munch<5.0,>=4.0
Requires-Dist: pydantic<3.0.0,>=2.4.2
Requires-Dist: pytz>=2023.3
Requires-Dist: pyyaml<7.0,>=6.0
Requires-Dist: setuptools>=70.0
Requires-Dist: structlog<24.0,>=23.1
Provides-Extra: gcp
Requires-Dist: google-cloud-secret-manager<3.0.0,>=2.16.4; extra == 'gcp'
